LICENSE
README.md
setup.py
arve/__init__.py
arve/arve.py
arve.egg-info/PKG-INFO
arve.egg-info/SOURCES.txt
arve.egg-info/dependency_links.txt
arve.egg-info/requires.txt
arve.egg-info/top_level.txt
arve/aux_data/__init__.py
arve/aux_data/masks/F0.csv.zip
arve/aux_data/masks/F2.csv.zip
arve/aux_data/masks/F5.csv.zip
arve/aux_data/masks/F8.csv.zip
arve/aux_data/masks/G0.csv.zip
arve/aux_data/masks/G2.csv.zip
arve/aux_data/masks/G5.csv.zip
arve/aux_data/masks/G8.csv.zip
arve/aux_data/masks/K0.csv.zip
arve/aux_data/masks/K2.csv.zip
arve/aux_data/masks/K3.csv.zip
arve/aux_data/masks/K5.csv.zip
arve/aux_data/masks/K7.csv.zip
arve/aux_data/masks/M0.csv.zip
arve/aux_data/masks/M2.csv.zip
arve/aux_data/masks/M5.csv.zip
arve/aux_data/spectra/F0.csv.zip
arve/aux_data/tellurics/TELL.csv.zip
arve/aux_data/wavelengths/WAVE.csv.zip
arve/data/__init__.py
arve/data/add_data.py
arve/data/compute_spec_reference.py
arve/data/compute_vrad_ccf.py
arve/data/compute_vrad_lbl.py
arve/data/get_aux_data.py
arve/data/plot_spec_data.py
arve/data/plot_vrad.py
arve/data/read_spec.py
arve/functions/__init__.py
arve/functions/convert_air_to_vac.py
arve/functions/convert_vac_to_air.py
arve/functions/doppler_shift.py
arve/functions/gls_periodogram.py
arve/functions/inverted_gaussian.py
arve/functions/keplerian.py
arve/functions/sptype_to_num.py
arve/planets/__init__.py
arve/planets/fit_keplerians.py
arve/planets/injection_recovery.py
arve/planets/plot_keplerians.py
arve/planets/plot_recoveries.py
arve/planets/recovery_test.py
arve/star/__init__.py
arve/star/add_vpsd_components.py
arve/star/compute_vpsd.py
arve/star/fit_vpsd_coefficients.py
arve/star/get_stellar_parameters.py
arve/star/plot_vpsd_components.py
arve/star/simulate_vrad_from_vpsd_components.py