Metadata-Version: 2.4
Name: arve
Version: 0.8.0
Summary: Analyzing Radial Velocity Elements
Home-page: https://github.com/almoulla/arve
Author: Khaled Al Moulla
Author-email: khaled.almoulla@gmail.com
License: MIT License
Classifier: Development Status :: 1 - Planning
Classifier: Intended Audience :: Science/Research
Classifier: License :: OSI Approved :: MIT License
Classifier: Programming Language :: Python :: 3
Requires-Python: >=3.10
License-File: LICENSE
Requires-Dist: astropy>=6.1.7
Requires-Dist: astroquery>=0.4.10
Requires-Dist: lmfit>=1.3.3
Requires-Dist: matplotlib>=3.10.1
Requires-Dist: numpy>=2.2.4
Requires-Dist: pandas>=2.2.3
Requires-Dist: scipy>=1.15.2
Requires-Dist: tqdm>=4.67.1
Dynamic: author
Dynamic: author-email
Dynamic: classifier
Dynamic: description
Dynamic: description-content-type
Dynamic: home-page
Dynamic: license
Dynamic: license-file
Dynamic: requires-dist
Dynamic: requires-python
Dynamic: summary
